notetoself.py
notetoself-1.0.3.dist-info/METADATA
notetoself-1.0.3.dist-info/RECORD
notetoself-1.0.3.dist-info/WHEEL
notetoself-1.0.3.dist-info/entry_points.txt
notetoself-1.0.3.dist-info/top_level.txt
nts/__init__.py
nts/api.py
nts/fstring.py
nts/ui/__init__.py
nts/ui/create.py
nts/ui/delete.py
nts/ui/edit.py
nts/ui/search.py
