Metadata-Version: 2.1
Name: notetoself
Version: 1.0.3
Summary: Note To Self -- Quick note taking tool
Home-page: https://gitlab.com/admicos/nts
Author: Ecmel B. CANLIER
Author-email: me@ecmelberk.com
License: Apache License Version 2.0
Keywords: note
Platform: UNKNOWN
Classifier: Development Status :: 4 - Beta
Classifier: Environment :: Console
Classifier: License :: OSI Approved :: Apache Software License
Classifier: Programming Language :: Python :: 3
Requires-Dist: appdirs
Requires-Dist: colorama
Requires-Dist: commonmark (<0.8.0)
Requires-Dist: consolemd
